[{"abyssinian": 0.0, "american_bulldog": 0.0, "american_pit_bull_terrier": 20.0, "basset_hound": 45.0, "beagle": 75.0, "bengal": 0.0, "birman": 25.0, "bombay": 0.0, "boxer": 0.0, "british_shorthair": 25.0, "chihuahua": 65.0, "egyptian_mau": 31.57894736842105, "english_cocker_spaniel": 10.526315789473685, "english_setter": 95.0, "german_shorthaired": 10.0, "great_pyrenees": 40.0, "havanese": 0.0, "japanese_chin": 90.0, "keeshond": 100.0, "leonberger": 55.0, "maine_coon": 30.0, "miniature_pinscher": 5.0, "newfoundland": 0.0, "persian": 0.0, "pomeranian": 75.0, "pug": 100.0, "ragdoll": 20.0, "russian_blue": 15.0, "saint_bernard": 5.0, "samoyed": 45.0, "scottish_terrier": 0.0, "shiba_inu": 70.0, "siamese": 15.0, "sphynx": 65.0, "staffordshire_bull_terrier": 40.0, "wheaten_terrier": 100.0, "yorkshire_terrier": 10.0}, {"abyssinian": 30.0, "american_bulldog": 55.0, "american_pit_bull_terrier": 60.0, "basset_hound": 85.0, "beagle": 90.0, "bengal": 5.0, "birman": 0.0, "bombay": 0.0, "boxer": 60.0, "british_shorthair": 0.0, "chihuahua": 75.0, "egyptian_mau": 31.57894736842105, "english_cocker_spaniel": 0.0, "english_setter": 10.0, "german_shorthaired": 55.0, "great_pyrenees": 80.0, "havanese": 5.0, "japanese_chin": 70.0, "keeshond": 55.0, "leonberger": 65.0, "maine_coon": 0.0, "miniature_pinscher": 5.0, "newfoundland": 21.05263157894737, "persian": 0.0, "pomeranian": 50.0, "pug": 100.0, "ragdoll": 70.0, "russian_blue": 40.0, "saint_bernard": 40.0, "samoyed": 95.0, "scottish_terrier": 50.0, "shiba_inu": 75.0, "siamese": 20.0, "sphynx": 100.0, "staffordshire_bull_terrier": 0.0, "wheaten_terrier": 85.0, "yorkshire_terrier": 5.0}, {"abyssinian": 40.0, "american_bulldog": 65.0, "american_pit_bull_terrier": 65.0, "basset_hound": 80.0, "beagle": 100.0, "bengal": 5.0, "birman": 0.0, "bombay": 5.2631578947368425, "boxer": 45.0, "british_shorthair": 5.0, "chihuahua": 90.0, "egyptian_mau": 84.21052631578948, "english_cocker_spaniel": 26.31578947368421, "english_setter": 0.0, "german_shorthaired": 10.0, "great_pyrenees": 80.0, "havanese": 15.0, "japanese_chin": 70.0, "keeshond": 70.0, "leonberger": 65.0, "maine_coon": 0.0, "miniature_pinscher": 60.0, "newfoundland": 73.6842105263158, "persian": 0.0, "pomeranian": 35.0, "pug": 100.0, "ragdoll": 95.0, "russian_blue": 85.0, "saint_bernard": 35.0, "samoyed": 90.0, "scottish_terrier": 75.0, "shiba_inu": 80.0, "siamese": 30.0, "sphynx": 95.0, "staffordshire_bull_terrier": 35.0, "wheaten_terrier": 90.0, "yorkshire_terrier": 15.0}, {"abyssinian": 50.0, "american_bulldog": 70.0, "american_pit_bull_terrier": 65.0, "basset_hound": 60.0, "beagle": 100.0, "bengal": 20.0, "birman": 0.0, "bombay": 0.0, "boxer": 45.0, "british_shorthair": 5.0, "chihuahua": 90.0, "egyptian_mau": 68.42105263157895, "english_cocker_spaniel": 31.57894736842105, "english_setter": 5.0, "german_shorthaired": 45.0, "great_pyrenees": 85.0, "havanese": 30.0, "japanese_chin": 75.0, "keeshond": 55.0, "leonberger": 40.0, "maine_coon": 20.0, "miniature_pinscher": 45.0, "newfoundland": 78.94736842105263, "persian": 20.0, "pomeranian": 50.0, "pug": 100.0, "ragdoll": 45.0, "russian_blue": 95.0, "saint_bernard": 20.0, "samoyed": 90.0, "scottish_terrier": 80.0, "shiba_inu": 80.0, "siamese": 35.0, "sphynx": 95.0, "staffordshire_bull_terrier": 45.0, "wheaten_terrier": 85.0, "yorkshire_terrier": 25.0}, {"abyssinian": 60.0, "american_bulldog": 60.0, "american_pit_bull_terrier": 70.0, "basset_hound": 85.0, "beagle": 85.0, "bengal": 25.0, "birman": 0.0, "bombay": 0.0, "boxer": 50.0, "british_shorthair": 15.0, "chihuahua": 90.0, "egyptian_mau": 57.89473684210526, "english_cocker_spaniel": 21.05263157894737, "english_setter": 15.0, "german_shorthaired": 20.0, "great_pyrenees": 90.0, "havanese": 25.0, "japanese_chin": 85.0, "keeshond": 30.0, "leonberger": 40.0, "maine_coon": 60.0, "miniature_pinscher": 35.0, "newfoundland": 73.6842105263158, "persian": 35.0, "pomeranian": 65.0, "pug": 100.0, "ragdoll": 25.0, "russian_blue": 100.0, "saint_bernard": 30.0, "samoyed": 85.0, "scottish_terrier": 75.0, "shiba_inu": 75.0, "siamese": 35.0, "sphynx": 95.0, "staffordshire_bull_terrier": 40.0, "wheaten_terrier": 85.0, "yorkshire_terrier": 30.0}, {"abyssinian": 55.0, "american_bulldog": 65.0, "american_pit_bull_terrier": 75.0, "basset_hound": 85.0, "beagle": 65.0, "bengal": 30.0, "birman": 0.0, "bombay": 0.0, "boxer": 35.0, "british_shorthair": 10.0, "chihuahua": 90.0, "egyptian_mau": 52.63157894736842, "english_cocker_spaniel": 31.57894736842105, "english_setter": 15.0, "german_shorthaired": 20.0, "great_pyrenees": 90.0, "havanese": 50.0, "japanese_chin": 85.0, "keeshond": 45.0, "leonberger": 20.0, "maine_coon": 50.0, "miniature_pinscher": 65.0, "newfoundland": 68.42105263157895, "persian": 25.0, "pomeranian": 70.0, "pug": 100.0, "ragdoll": 25.0, "russian_blue": 100.0, "saint_bernard": 55.0, "samoyed": 90.0, "scottish_terrier": 80.0, "shiba_inu": 80.0, "siamese": 30.0, "sphynx": 90.0, "staffordshire_bull_terrier": 45.0, "wheaten_terrier": 80.0, "yorkshire_terrier": 30.0}, {"abyssinian": 25.0, "american_bulldog": 70.0, "american_pit_bull_terrier": 45.0, "basset_hound": 85.0, "beagle": 50.0, "bengal": 45.0, "birman": 0.0, "bombay": 0.0, "boxer": 30.0, "british_shorthair": 5.0, "chihuahua": 80.0, "egyptian_mau": 42.10526315789474, "english_cocker_spaniel": 36.8421052631579, "english_setter": 15.0, "german_shorthaired": 20.0, "great_pyrenees": 90.0, "havanese": 40.0, "japanese_chin": 85.0, "keeshond": 35.0, "leonberger": 20.0, "maine_coon": 20.0, "miniature_pinscher": 70.0, "newfoundland": 68.42105263157895, "persian": 35.0, "pomeranian": 65.0, "pug": 100.0, "ragdoll": 25.0, "russian_blue": 95.0, "saint_bernard": 60.0, "samoyed": 90.0, "scottish_terrier": 75.0, "shiba_inu": 75.0, "siamese": 25.0, "sphynx": 85.0, "staffordshire_bull_terrier": 60.0, "wheaten_terrier": 45.0, "yorkshire_terrier": 20.0}, {"abyssinian": 10.0, "american_bulldog": 30.0, "american_pit_bull_terrier": 35.0, "basset_hound": 75.0, "beagle": 45.0, "bengal": 40.0, "birman": 0.0, "bombay": 0.0, "boxer": 30.0, "british_shorthair": 0.0, "chihuahua": 75.0, "egyptian_mau": 15.789473684210526, "english_cocker_spaniel": 52.63157894736842, "english_setter": 15.0, "german_shorthaired": 20.0, "great_pyrenees": 90.0, "havanese": 30.0, "japanese_chin": 80.0, "keeshond": 20.0, "leonberger": 20.0, "maine_coon": 25.0, "miniature_pinscher": 65.0, "newfoundland": 63.1578947368421, "persian": 25.0, "pomeranian": 70.0, "pug": 100.0, "ragdoll": 20.0, "russian_blue": 85.0, "saint_bernard": 55.0, "samoyed": 70.0, "scottish_terrier": 55.0, "shiba_inu": 75.0, "siamese": 25.0, "sphynx": 95.0, "staffordshire_bull_terrier": 65.0, "wheaten_terrier": 5.0, "yorkshire_terrier": 15.0}, {"abyssinian": 0.0, "american_bulldog": 55.0, "american_pit_bull_terrier": 35.0, "basset_hound": 85.0, "beagle": 50.0, "bengal": 35.0, "birman": 20.0, "bombay": 0.0, "boxer": 30.0, "british_shorthair": 5.0, "chihuahua": 80.0, "egyptian_mau": 52.63157894736842, "english_cocker_spaniel": 47.36842105263158, "english_setter": 5.0, "german_shorthaired": 25.0, "great_pyrenees": 90.0, "havanese": 40.0, "japanese_chin": 80.0, "keeshond": 20.0, "leonberger": 25.0, "maine_coon": 75.0, "miniature_pinscher": 70.0, "newfoundland": 73.6842105263158, "persian": 20.0, "pomeranian": 75.0, "pug": 100.0, "ragdoll": 30.0, "russian_blue": 75.0, "saint_bernard": 55.0, "samoyed": 90.0, "scottish_terrier": 65.0, "shiba_inu": 80.0, "siamese": 35.0, "sphynx": 90.0, "staffordshire_bull_terrier": 75.0, "wheaten_terrier": 50.0, "yorkshire_terrier": 15.0}, {"abyssinian": 5.0, "american_bulldog": 25.0, "american_pit_bull_terrier": 35.0, "basset_hound": 85.0, "beagle": 35.0, "bengal": 35.0, "birman": 30.0, "bombay": 0.0, "boxer": 30.0, "british_shorthair": 5.0, "chihuahua": 75.0, "egyptian_mau": 36.8421052631579, "english_cocker_spaniel": 47.36842105263158, "english_setter": 15.0, "german_shorthaired": 20.0, "great_pyrenees": 90.0, "havanese": 45.0, "japanese_chin": 80.0, "keeshond": 25.0, "leonberger": 30.0, "maine_coon": 65.0, "miniature_pinscher": 85.0, "newfoundland": 68.42105263157895, "persian": 20.0, "pomeranian": 80.0, "pug": 100.0, "ragdoll": 20.0, "russian_blue": 85.0, "saint_bernard": 60.0, "samoyed": 90.0, "scottish_terrier": 65.0, "shiba_inu": 80.0, "siamese": 35.0, "sphynx": 95.0, "staffordshire_bull_terrier": 65.0, "wheaten_terrier": 45.0, "yorkshire_terrier": 15.0}, {"abyssinian": 5.0, "american_bulldog": 25.0, "american_pit_bull_terrier": 30.0, "basset_hound": 85.0, "beagle": 25.0, "bengal": 30.0, "birman": 25.0, "bombay": 0.0, "boxer": 25.0, "british_shorthair": 0.0, "chihuahua": 80.0, "egyptian_mau": 47.36842105263158, "english_cocker_spaniel": 47.36842105263158, "english_setter": 15.0, "german_shorthaired": 20.0, "great_pyrenees": 90.0, "havanese": 50.0, "japanese_chin": 80.0, "keeshond": 10.0, "leonberger": 25.0, "maine_coon": 65.0, "miniature_pinscher": 70.0, "newfoundland": 73.6842105263158, "persian": 20.0, "pomeranian": 70.0, "pug": 100.0, "ragdoll": 10.0, "russian_blue": 90.0, "saint_bernard": 60.0, "samoyed": 90.0, "scottish_terrier": 65.0, "shiba_inu": 80.0, "siamese": 35.0, "sphynx": 85.0, "staffordshire_bull_terrier": 75.0, "wheaten_terrier": 25.0, "yorkshire_terrier": 15.0}, {"abyssinian": 0.0, "american_bulldog": 25.0, "american_pit_bull_terrier": 25.0, "basset_hound": 90.0, "beagle": 30.0, "bengal": 35.0, "birman": 10.0, "bombay": 0.0, "boxer": 25.0, "british_shorthair": 0.0, "chihuahua": 80.0, "egyptian_mau": 47.36842105263158, "english_cocker_spaniel": 47.36842105263158, "english_setter": 15.0, "german_shorthaired": 20.0, "great_pyrenees": 90.0, "havanese": 45.0, "japanese_chin": 65.0, "keeshond": 5.0, "leonberger": 20.0, "maine_coon": 45.0, "miniature_pinscher": 70.0, "newfoundland": 68.42105263157895, "persian": 40.0, "pomeranian": 85.0, "pug": 100.0, "ragdoll": 10.0, "russian_blue": 85.0, "saint_bernard": 60.0, "samoyed": 75.0, "scottish_terrier": 60.0, "shiba_inu": 80.0, "siamese": 45.0, "sphynx": 80.0, "staffordshire_bull_terrier": 75.0, "wheaten_terrier": 25.0, "yorkshire_terrier": 15.0}, {"abyssinian": 0.0, "american_bulldog": 30.0, "american_pit_bull_terrier": 30.0, "basset_hound": 95.0, "beagle": 20.0, "bengal": 30.0, "birman": 25.0, "bombay": 0.0, "boxer": 35.0, "british_shorthair": 5.0, "chihuahua": 80.0, "egyptian_mau": 57.89473684210526, "english_cocker_spaniel": 47.36842105263158, "english_setter": 20.0, "german_shorthaired": 25.0, "great_pyrenees": 90.0, "havanese": 50.0, "japanese_chin": 80.0, "keeshond": 15.0, "leonberger": 30.0, "maine_coon": 65.0, "miniature_pinscher": 80.0, "newfoundland": 73.6842105263158, "persian": 20.0, "pomeranian": 85.0, "pug": 100.0, "ragdoll": 20.0, "russian_blue": 85.0, "saint_bernard": 60.0, "samoyed": 85.0, "scottish_terrier": 75.0, "shiba_inu": 85.0, "siamese": 35.0, "sphynx": 85.0, "staffordshire_bull_terrier": 75.0, "wheaten_terrier": 55.0, "yorkshire_terrier": 15.0}, {"abyssinian": 5.0, "american_bulldog": 25.0, "american_pit_bull_terrier": 30.0, "basset_hound": 90.0, "beagle": 25.0, "bengal": 35.0, "birman": 25.0, "bombay": 0.0, "boxer": 25.0, "british_shorthair": 5.0, "chihuahua": 80.0, "egyptian_mau": 31.57894736842105, "english_cocker_spaniel": 47.36842105263158, "english_setter": 10.0, "german_shorthaired": 20.0, "great_pyrenees": 90.0, "havanese": 40.0, "japanese_chin": 80.0, "keeshond": 10.0, "leonberger": 20.0, "maine_coon": 65.0, "miniature_pinscher": 75.0, "newfoundland": 68.42105263157895, "persian": 30.0, "pomeranian": 80.0, "pug": 100.0, "ragdoll": 10.0, "russian_blue": 90.0, "saint_bernard": 60.0, "samoyed": 75.0, "scottish_terrier": 60.0, "shiba_inu": 80.0, "siamese": 30.0, "sphynx": 85.0, "staffordshire_bull_terrier": 75.0, "wheaten_terrier": 40.0, "yorkshire_terrier": 15.0}, {"abyssinian": 0.0, "american_bulldog": 25.0, "american_pit_bull_terrier": 35.0, "basset_hound": 90.0, "beagle": 30.0, "bengal": 35.0, "birman": 5.0, "bombay": 0.0, "boxer": 25.0, "british_shorthair": 0.0, "chihuahua": 80.0, "egyptian_mau": 42.10526315789474, "english_cocker_spaniel": 52.63157894736842, "english_setter": 5.0, "german_shorthaired": 20.0, "great_pyrenees": 90.0, "havanese": 45.0, "japanese_chin": 60.0, "keeshond": 5.0, "leonberger": 35.0, "maine_coon": 65.0, "miniature_pinscher": 65.0, "newfoundland": 73.6842105263158, "persian": 40.0, "pomeranian": 70.0, "pug": 100.0, "ragdoll": 20.0, "russian_blue": 85.0, "saint_bernard": 55.0, "samoyed": 80.0, "scottish_terrier": 60.0, "shiba_inu": 80.0, "siamese": 35.0, "sphynx": 75.0, "staffordshire_bull_terrier": 75.0, "wheaten_terrier": 55.0, "yorkshire_terrier": 15.0}, {"abyssinian": 5.0, "american_bulldog": 25.0, "american_pit_bull_terrier": 30.0, "basset_hound": 90.0, "beagle": 20.0, "bengal": 30.0, "birman": 5.0, "bombay": 0.0, "boxer": 25.0, "british_shorthair": 5.0, "chihuahua": 80.0, "egyptian_mau": 36.8421052631579, "english_cocker_spaniel": 47.36842105263158, "english_setter": 5.0, "german_shorthaired": 20.0, "great_pyrenees": 90.0, "havanese": 40.0, "japanese_chin": 65.0, "keeshond": 15.0, "leonberger": 25.0, "maine_coon": 70.0, "miniature_pinscher": 65.0, "newfoundland": 73.6842105263158, "persian": 40.0, "pomeranian": 65.0, "pug": 100.0, "ragdoll": 10.0, "russian_blue": 90.0, "saint_bernard": 60.0, "samoyed": 80.0, "scottish_terrier": 60.0, "shiba_inu": 80.0, "siamese": 65.0, "sphynx": 80.0, "staffordshire_bull_terrier": 75.0, "wheaten_terrier": 45.0, "yorkshire_terrier": 15.0}, {"abyssinian": 0.0, "american_bulldog": 30.0, "american_pit_bull_terrier": 30.0, "basset_hound": 95.0, "beagle": 30.0, "bengal": 30.0, "birman": 30.0, "bombay": 0.0, "boxer": 30.0, "british_shorthair": 0.0, "chihuahua": 85.0, "egyptian_mau": 63.1578947368421, "english_cocker_spaniel": 47.36842105263158, "english_setter": 5.0, "german_shorthaired": 25.0, "great_pyrenees": 90.0, "havanese": 40.0, "japanese_chin": 70.0, "keeshond": 10.0, "leonberger": 35.0, "maine_coon": 60.0, "miniature_pinscher": 60.0, "newfoundland": 73.6842105263158, "persian": 30.0, "pomeranian": 70.0, "pug": 100.0, "ragdoll": 10.0, "russian_blue": 85.0, "saint_bernard": 55.0, "samoyed": 80.0, "scottish_terrier": 70.0, "shiba_inu": 80.0, "siamese": 30.0, "sphynx": 70.0, "staffordshire_bull_terrier": 80.0, "wheaten_terrier": 60.0, "yorkshire_terrier": 15.0}, {"abyssinian": 0.0, "american_bulldog": 20.0, "american_pit_bull_terrier": 35.0, "basset_hound": 100.0, "beagle": 20.0, "bengal": 40.0, "birman": 25.0, "bombay": 0.0, "boxer": 20.0, "british_shorthair": 0.0, "chihuahua": 80.0, "egyptian_mau": 31.57894736842105, "english_cocker_spaniel": 57.89473684210526, "english_setter": 5.0, "german_shorthaired": 20.0, "great_pyrenees": 90.0, "havanese": 35.0, "japanese_chin": 80.0, "keeshond": 10.0, "leonberger": 40.0, "maine_coon": 50.0, "miniature_pinscher": 55.0, "newfoundland": 68.42105263157895, "persian": 40.0, "pomeranian": 70.0, "pug": 100.0, "ragdoll": 10.0, "russian_blue": 95.0, "saint_bernard": 65.0, "samoyed": 85.0, "scottish_terrier": 65.0, "shiba_inu": 80.0, "siamese": 30.0, "sphynx": 85.0, "staffordshire_bull_terrier": 70.0, "wheaten_terrier": 55.0, "yorkshire_terrier": 25.0}, {"abyssinian": 0.0, "american_bulldog": 25.0, "american_pit_bull_terrier": 30.0, "basset_hound": 90.0, "beagle": 20.0, "bengal": 35.0, "birman": 25.0, "bombay": 0.0, "boxer": 25.0, "british_shorthair": 0.0, "chihuahua": 85.0, "egyptian_mau": 31.57894736842105, "english_cocker_spaniel": 52.63157894736842, "english_setter": 10.0, "german_shorthaired": 20.0, "great_pyrenees": 90.0, "havanese": 35.0, "japanese_chin": 80.0, "keeshond": 10.0, "leonberger": 45.0, "maine_coon": 65.0, "miniature_pinscher": 60.0, "newfoundland": 68.42105263157895, "persian": 25.0, "pomeranian": 60.0, "pug": 100.0, "ragdoll": 10.0, "russian_blue": 95.0, "saint_bernard": 60.0, "samoyed": 75.0, "scottish_terrier": 60.0, "shiba_inu": 80.0, "siamese": 25.0, "sphynx": 90.0, "staffordshire_bull_terrier": 65.0, "wheaten_terrier": 45.0, "yorkshire_terrier": 20.0}, {"abyssinian": 0.0, "american_bulldog": 20.0, "american_pit_bull_terrier": 35.0, "basset_hound": 100.0, "beagle": 20.0, "bengal": 25.0, "birman": 15.0, "bombay": 0.0, "boxer": 25.0, "british_shorthair": 0.0, "chihuahua": 85.0, "egyptian_mau": 42.10526315789474, "english_cocker_spaniel": 57.89473684210526, "english_setter": 15.0, "german_shorthaired": 25.0, "great_pyrenees": 90.0, "havanese": 25.0, "japanese_chin": 80.0, "keeshond": 15.0, "leonberger": 50.0, "maine_coon": 65.0, "miniature_pinscher": 65.0, "newfoundland": 73.6842105263158, "persian": 40.0, "pomeranian": 60.0, "pug": 100.0, "ragdoll": 10.0, "russian_blue": 95.0, "saint_bernard": 60.0, "samoyed": 75.0, "scottish_terrier": 60.0, "shiba_inu": 85.0, "siamese": 45.0, "sphynx": 90.0, "staffordshire_bull_terrier": 75.0, "wheaten_terrier": 50.0, "yorkshire_terrier": 25.0}, {"abyssinian": 0.0, "american_bulldog": 25.0, "american_pit_bull_terrier": 35.0, "basset_hound": 100.0, "beagle": 20.0, "bengal": 40.0, "birman": 35.0, "bombay": 10.526315789473685, "boxer": 25.0, "british_shorthair": 0.0, "chihuahua": 85.0, "egyptian_mau": 31.57894736842105, "english_cocker_spaniel": 57.89473684210526, "english_setter": 15.0, "german_shorthaired": 30.0, "great_pyrenees": 90.0, "havanese": 20.0, "japanese_chin": 75.0, "keeshond": 5.0, "leonberger": 45.0, "maine_coon": 65.0, "miniature_pinscher": 55.0, "newfoundland": 73.6842105263158, "persian": 30.0, "pomeranian": 60.0, "pug": 100.0, "ragdoll": 10.0, "russian_blue": 90.0, "saint_bernard": 60.0, "samoyed": 80.0, "scottish_terrier": 70.0, "shiba_inu": 80.0, "siamese": 25.0, "sphynx": 65.0, "staffordshire_bull_terrier": 75.0, "wheaten_terrier": 50.0, "yorkshire_terrier": 15.0}, {"abyssinian": 0.0, "american_bulldog": 25.0, "american_pit_bull_terrier": 35.0, "basset_hound": 95.0, "beagle": 20.0, "bengal": 25.0, "birman": 35.0, "bombay": 0.0, "boxer": 40.0, "british_shorthair": 0.0, "chihuahua": 80.0, "egyptian_mau": 47.36842105263158, "english_cocker_spaniel": 57.89473684210526, "english_setter": 15.0, "german_shorthaired": 35.0, "great_pyrenees": 90.0, "havanese": 25.0, "japanese_chin": 80.0, "keeshond": 5.0, "leonberger": 60.0, "maine_coon": 60.0, "miniature_pinscher": 70.0, "newfoundland": 73.6842105263158, "persian": 30.0, "pomeranian": 60.0, "pug": 100.0, "ragdoll": 10.0, "russian_blue": 90.0, "saint_bernard": 65.0, "samoyed": 90.0, "scottish_terrier": 65.0, "shiba_inu": 80.0, "siamese": 40.0, "sphynx": 90.0, "staffordshire_bull_terrier": 75.0, "wheaten_terrier": 50.0, "yorkshire_terrier": 25.0}, {"abyssinian": 0.0, "american_bulldog": 25.0, "american_pit_bull_terrier": 35.0, "basset_hound": 100.0, "beagle": 20.0, "bengal": 35.0, "birman": 30.0, "bombay": 5.2631578947368425, "boxer": 30.0, "british_shorthair": 5.0, "chihuahua": 80.0, "egyptian_mau": 47.36842105263158, "english_cocker_spaniel": 47.36842105263158, "english_setter": 20.0, "german_shorthaired": 30.0, "great_pyrenees": 90.0, "havanese": 40.0, "japanese_chin": 80.0, "keeshond": 15.0, "leonberger": 50.0, "maine_coon": 65.0, "miniature_pinscher": 75.0, "newfoundland": 73.6842105263158, "persian": 45.0, "pomeranian": 70.0, "pug": 100.0, "ragdoll": 10.0, "russian_blue": 95.0, "saint_bernard": 65.0, "samoyed": 90.0, "scottish_terrier": 70.0, "shiba_inu": 85.0, "siamese": 30.0, "sphynx": 85.0, "staffordshire_bull_terrier": 70.0, "wheaten_terrier": 60.0, "yorkshire_terrier": 30.0}, {"abyssinian": 0.0, "american_bulldog": 25.0, "american_pit_bull_terrier": 40.0, "basset_hound": 95.0, "beagle": 20.0, "bengal": 35.0, "birman": 25.0, "bombay": 10.526315789473685, "boxer": 40.0, "british_shorthair": 0.0, "chihuahua": 80.0, "egyptian_mau": 42.10526315789474, "english_cocker_spaniel": 63.1578947368421, "english_setter": 10.0, "german_shorthaired": 20.0, "great_pyrenees": 90.0, "havanese": 20.0, "japanese_chin": 70.0, "keeshond": 5.0, "leonberger": 40.0, "maine_coon": 65.0, "miniature_pinscher": 70.0, "newfoundland": 78.94736842105263, "persian": 20.0, "pomeranian": 80.0, "pug": 100.0, "ragdoll": 10.0, "russian_blue": 95.0, "saint_bernard": 60.0, "samoyed": 85.0, "scottish_terrier": 70.0, "shiba_inu": 85.0, "siamese": 25.0, "sphynx": 70.0, "staffordshire_bull_terrier": 70.0, "wheaten_terrier": 60.0, "yorkshire_terrier": 25.0}, {"abyssinian": 0.0, "american_bulldog": 25.0, "american_pit_bull_terrier": 35.0, "basset_hound": 95.0, "beagle": 25.0, "bengal": 35.0, "birman": 10.0, "bombay": 10.526315789473685, "boxer": 30.0, "british_shorthair": 0.0, "chihuahua": 85.0, "egyptian_mau": 31.57894736842105, "english_cocker_spaniel": 63.1578947368421, "english_setter": 5.0, "german_shorthaired": 30.0, "great_pyrenees": 90.0, "havanese": 20.0, "japanese_chin": 65.0, "keeshond": 5.0, "leonberger": 45.0, "maine_coon": 65.0, "miniature_pinscher": 65.0, "newfoundland": 73.6842105263158, "persian": 45.0, "pomeranian": 65.0, "pug": 100.0, "ragdoll": 10.0, "russian_blue": 95.0, "saint_bernard": 60.0, "samoyed": 75.0, "scottish_terrier": 65.0, "shiba_inu": 85.0, "siamese": 50.0, "sphynx": 60.0, "staffordshire_bull_terrier": 75.0, "wheaten_terrier": 55.0, "yorkshire_terrier": 20.0}, {"abyssinian": 0.0, "american_bulldog": 25.0, "american_pit_bull_terrier": 35.0, "basset_hound": 95.0, "beagle": 20.0, "bengal": 45.0, "birman": 15.0, "bombay": 10.526315789473685, "boxer": 50.0, "british_shorthair": 0.0, "chihuahua": 85.0, "egyptian_mau": 42.10526315789474, "english_cocker_spaniel": 63.1578947368421, "english_setter": 15.0, "german_shorthaired": 35.0, "great_pyrenees": 90.0, "havanese": 15.0, "japanese_chin": 75.0, "keeshond": 10.0, "leonberger": 45.0, "maine_coon": 65.0, "miniature_pinscher": 65.0, "newfoundland": 73.6842105263158, "persian": 40.0, "pomeranian": 75.0, "pug": 100.0, "ragdoll": 10.0, "russian_blue": 90.0, "saint_bernard": 60.0, "samoyed": 85.0, "scottish_terrier": 65.0, "shiba_inu": 85.0, "siamese": 40.0, "sphynx": 45.0, "staffordshire_bull_terrier": 75.0, "wheaten_terrier": 50.0, "yorkshire_terrier": 15.0}, {"abyssinian": 0.0, "american_bulldog": 25.0, "american_pit_bull_terrier": 35.0, "basset_hound": 95.0, "beagle": 20.0, "bengal": 35.0, "birman": 35.0, "bombay": 5.2631578947368425, "boxer": 50.0, "british_shorthair": 0.0, "chihuahua": 85.0, "egyptian_mau": 52.63157894736842, "english_cocker_spaniel": 63.1578947368421, "english_setter": 15.0, "german_shorthaired": 35.0, "great_pyrenees": 90.0, "havanese": 15.0, "japanese_chin": 65.0, "keeshond": 15.0, "leonberger": 45.0, "maine_coon": 60.0, "miniature_pinscher": 65.0, "newfoundland": 73.6842105263158, "persian": 30.0, "pomeranian": 65.0, "pug": 100.0, "ragdoll": 10.0, "russian_blue": 90.0, "saint_bernard": 60.0, "samoyed": 90.0, "scottish_terrier": 70.0, "shiba_inu": 80.0, "siamese": 35.0, "sphynx": 50.0, "staffordshire_bull_terrier": 70.0, "wheaten_terrier": 50.0, "yorkshire_terrier": 15.0}, {"abyssinian": 0.0, "american_bulldog": 25.0, "american_pit_bull_terrier": 35.0, "basset_hound": 100.0, "beagle": 20.0, "bengal": 35.0, "birman": 25.0, "bombay": 0.0, "boxer": 45.0, "british_shorthair": 0.0, "chihuahua": 85.0, "egyptian_mau": 42.10526315789474, "english_cocker_spaniel": 57.89473684210526, "english_setter": 20.0, "german_shorthaired": 40.0, "great_pyrenees": 85.0, "havanese": 15.0, "japanese_chin": 75.0, "keeshond": 15.0, "leonberger": 60.0, "maine_coon": 55.0, "miniature_pinscher": 75.0, "newfoundland": 73.6842105263158, "persian": 30.0, "pomeranian": 60.0, "pug": 100.0, "ragdoll": 10.0, "russian_blue": 95.0, "saint_bernard": 65.0, "samoyed": 90.0, "scottish_terrier": 70.0, "shiba_inu": 80.0, "siamese": 65.0, "sphynx": 65.0, "staffordshire_bull_terrier": 75.0, "wheaten_terrier": 55.0, "yorkshire_terrier": 15.0}, {"abyssinian": 0.0, "american_bulldog": 25.0, "american_pit_bull_terrier": 35.0, "basset_hound": 100.0, "beagle": 20.0, "bengal": 35.0, "birman": 25.0, "bombay": 10.526315789473685, "boxer": 40.0, "british_shorthair": 0.0, "chihuahua": 85.0, "egyptian_mau": 31.57894736842105, "english_cocker_spaniel": 57.89473684210526, "english_setter": 15.0, "german_shorthaired": 35.0, "great_pyrenees": 85.0, "havanese": 15.0, "japanese_chin": 75.0, "keeshond": 15.0, "leonberger": 50.0, "maine_coon": 70.0, "miniature_pinscher": 65.0, "newfoundland": 73.6842105263158, "persian": 25.0, "pomeranian": 60.0, "pug": 100.0, "ragdoll": 10.0, "russian_blue": 95.0, "saint_bernard": 60.0, "samoyed": 80.0, "scottish_terrier": 65.0, "shiba_inu": 80.0, "siamese": 55.0, "sphynx": 50.0, "staffordshire_bull_terrier": 80.0, "wheaten_terrier": 50.0, "yorkshire_terrier": 20.0}, {"abyssinian": 0.0, "american_bulldog": 25.0, "american_pit_bull_terrier": 35.0, "basset_hound": 95.0, "beagle": 20.0, "bengal": 30.0, "birman": 25.0, "bombay": 10.526315789473685, "boxer": 45.0, "british_shorthair": 0.0, "chihuahua": 85.0, "egyptian_mau": 31.57894736842105, "english_cocker_spaniel": 63.1578947368421, "english_setter": 15.0, "german_shorthaired": 35.0, "great_pyrenees": 90.0, "havanese": 20.0, "japanese_chin": 60.0, "keeshond": 5.0, "leonberger": 45.0, "maine_coon": 60.0, "miniature_pinscher": 65.0, "newfoundland": 68.42105263157895, "persian": 45.0, "pomeranian": 60.0, "pug": 100.0, "ragdoll": 10.0, "russian_blue": 95.0, "saint_bernard": 60.0, "samoyed": 75.0, "scottish_terrier": 60.0, "shiba_inu": 80.0, "siamese": 50.0, "sphynx": 35.0, "staffordshire_bull_terrier": 75.0, "wheaten_terrier": 50.0, "yorkshire_terrier": 15.0}, {"abyssinian": 0.0, "american_bulldog": 35.0, "american_pit_bull_terrier": 35.0, "basset_hound": 95.0, "beagle": 20.0, "bengal": 45.0, "birman": 30.0, "bombay": 15.789473684210526, "boxer": 50.0, "british_shorthair": 0.0, "chihuahua": 85.0, "egyptian_mau": 47.36842105263158, "english_cocker_spaniel": 63.1578947368421, "english_setter": 20.0, "german_shorthaired": 35.0, "great_pyrenees": 90.0, "havanese": 15.0, "japanese_chin": 60.0, "keeshond": 15.0, "leonberger": 50.0, "maine_coon": 75.0, "miniature_pinscher": 70.0, "newfoundland": 73.6842105263158, "persian": 20.0, "pomeranian": 80.0, "pug": 100.0, "ragdoll": 10.0, "russian_blue": 85.0, "saint_bernard": 60.0, "samoyed": 75.0, "scottish_terrier": 70.0, "shiba_inu": 80.0, "siamese": 40.0, "sphynx": 30.0, "staffordshire_bull_terrier": 75.0, "wheaten_terrier": 55.0, "yorkshire_terrier": 20.0}, {"abyssinian": 0.0, "american_bulldog": 25.0, "american_pit_bull_terrier": 35.0, "basset_hound": 100.0, "beagle": 20.0, "bengal": 30.0, "birman": 35.0, "bombay": 15.789473684210526, "boxer": 45.0, "british_shorthair": 0.0, "chihuahua": 80.0, "egyptian_mau": 36.8421052631579, "english_cocker_spaniel": 68.42105263157895, "english_setter": 20.0, "german_shorthaired": 40.0, "great_pyrenees": 90.0, "havanese": 15.0, "japanese_chin": 70.0, "keeshond": 10.0, "leonberger": 65.0, "maine_coon": 60.0, "miniature_pinscher": 70.0, "newfoundland": 73.6842105263158, "persian": 25.0, "pomeranian": 75.0, "pug": 100.0, "ragdoll": 10.0, "russian_blue": 90.0, "saint_bernard": 60.0, "samoyed": 90.0, "scottish_terrier": 70.0, "shiba_inu": 80.0, "siamese": 55.0, "sphynx": 65.0, "staffordshire_bull_terrier": 75.0, "wheaten_terrier": 50.0, "yorkshire_terrier": 20.0}, {"abyssinian": 0.0, "american_bulldog": 25.0, "american_pit_bull_terrier": 35.0, "basset_hound": 100.0, "beagle": 20.0, "bengal": 35.0, "birman": 45.0, "bombay": 10.526315789473685, "boxer": 45.0, "british_shorthair": 0.0, "chihuahua": 85.0, "egyptian_mau": 42.10526315789474, "english_cocker_spaniel": 52.63157894736842, "english_setter": 20.0, "german_shorthaired": 40.0, "great_pyrenees": 90.0, "havanese": 15.0, "japanese_chin": 75.0, "keeshond": 15.0, "leonberger": 65.0, "maine_coon": 55.0, "miniature_pinscher": 80.0, "newfoundland": 73.6842105263158, "persian": 25.0, "pomeranian": 65.0, "pug": 100.0, "ragdoll": 10.0, "russian_blue": 90.0, "saint_bernard": 60.0, "samoyed": 85.0, "scottish_terrier": 70.0, "shiba_inu": 80.0, "siamese": 60.0, "sphynx": 60.0, "staffordshire_bull_terrier": 75.0, "wheaten_terrier": 50.0, "yorkshire_terrier": 15.0}, {"abyssinian": 0.0, "american_bulldog": 30.0, "american_pit_bull_terrier": 35.0, "basset_hound": 100.0, "beagle": 20.0, "bengal": 35.0, "birman": 30.0, "bombay": 15.789473684210526, "boxer": 35.0, "british_shorthair": 0.0, "chihuahua": 85.0, "egyptian_mau": 42.10526315789474, "english_cocker_spaniel": 52.63157894736842, "english_setter": 20.0, "german_shorthaired": 40.0, "great_pyrenees": 90.0, "havanese": 15.0, "japanese_chin": 75.0, "keeshond": 15.0, "leonberger": 60.0, "maine_coon": 55.0, "miniature_pinscher": 80.0, "newfoundland": 73.6842105263158, "persian": 20.0, "pomeranian": 70.0, "pug": 100.0, "ragdoll": 10.0, "russian_blue": 90.0, "saint_bernard": 60.0, "samoyed": 85.0, "scottish_terrier": 70.0, "shiba_inu": 80.0, "siamese": 60.0, "sphynx": 45.0, "staffordshire_bull_terrier": 75.0, "wheaten_terrier": 50.0, "yorkshire_terrier": 15.0}, {"abyssinian": 0.0, "american_bulldog": 35.0, "american_pit_bull_terrier": 35.0, "basset_hound": 100.0, "beagle": 20.0, "bengal": 30.0, "birman": 40.0, "bombay": 15.789473684210526, "boxer": 40.0, "british_shorthair": 0.0, "chihuahua": 80.0, "egyptian_mau": 42.10526315789474, "english_cocker_spaniel": 57.89473684210526, "english_setter": 20.0, "german_shorthaired": 35.0, "great_pyrenees": 90.0, "havanese": 15.0, "japanese_chin": 75.0, "keeshond": 15.0, "leonberger": 65.0, "maine_coon": 75.0, "miniature_pinscher": 75.0, "newfoundland": 73.6842105263158, "persian": 15.0, "pomeranian": 70.0, "pug": 100.0, "ragdoll": 10.0, "russian_blue": 95.0, "saint_bernard": 60.0, "samoyed": 85.0, "scottish_terrier": 75.0, "shiba_inu": 80.0, "siamese": 60.0, "sphynx": 55.0, "staffordshire_bull_terrier": 75.0, "wheaten_terrier": 60.0, "yorkshire_terrier": 15.0}, {"abyssinian": 0.0, "american_bulldog": 30.0, "american_pit_bull_terrier": 35.0, "basset_hound": 100.0, "beagle": 20.0, "bengal": 30.0, "birman": 30.0, "bombay": 15.789473684210526, "boxer": 50.0, "british_shorthair": 0.0, "chihuahua": 85.0, "egyptian_mau": 47.36842105263158, "english_cocker_spaniel": 47.36842105263158, "english_setter": 20.0, "german_shorthaired": 40.0, "great_pyrenees": 90.0, "havanese": 15.0, "japanese_chin": 75.0, "keeshond": 15.0, "leonberger": 60.0, "maine_coon": 65.0, "miniature_pinscher": 65.0, "newfoundland": 73.6842105263158, "persian": 20.0, "pomeranian": 70.0, "pug": 100.0, "ragdoll": 10.0, "russian_blue": 95.0, "saint_bernard": 60.0, "samoyed": 85.0, "scottish_terrier": 70.0, "shiba_inu": 80.0, "siamese": 55.0, "sphynx": 50.0, "staffordshire_bull_terrier": 75.0, "wheaten_terrier": 55.0, "yorkshire_terrier": 20.0}, {"abyssinian": 0.0, "american_bulldog": 30.0, "american_pit_bull_terrier": 35.0, "basset_hound": 95.0, "beagle": 20.0, "bengal": 35.0, "birman": 30.0, "bombay": 10.526315789473685, "boxer": 30.0, "british_shorthair": 0.0, "chihuahua": 85.0, "egyptian_mau": 42.10526315789474, "english_cocker_spaniel": 42.10526315789474, "english_setter": 20.0, "german_shorthaired": 40.0, "great_pyrenees": 85.0, "havanese": 20.0, "japanese_chin": 75.0, "keeshond": 15.0, "leonberger": 60.0, "maine_coon": 85.0, "miniature_pinscher": 80.0, "newfoundland": 57.89473684210526, "persian": 20.0, "pomeranian": 85.0, "pug": 100.0, "ragdoll": 10.0, "russian_blue": 90.0, "saint_bernard": 60.0, "samoyed": 90.0, "scottish_terrier": 70.0, "shiba_inu": 80.0, "siamese": 60.0, "sphynx": 55.0, "staffordshire_bull_terrier": 75.0, "wheaten_terrier": 60.0, "yorkshire_terrier": 15.0}, {"abyssinian": 0.0, "american_bulldog": 35.0, "american_pit_bull_terrier": 35.0, "basset_hound": 95.0, "beagle": 20.0, "bengal": 40.0, "birman": 25.0, "bombay": 15.789473684210526, "boxer": 30.0, "british_shorthair": 0.0, "chihuahua": 85.0, "egyptian_mau": 42.10526315789474, "english_cocker_spaniel": 52.63157894736842, "english_setter": 20.0, "german_shorthaired": 40.0, "great_pyrenees": 90.0, "havanese": 15.0, "japanese_chin": 70.0, "keeshond": 15.0, "leonberger": 65.0, "maine_coon": 60.0, "miniature_pinscher": 75.0, "newfoundland": 63.1578947368421, "persian": 15.0, "pomeranian": 75.0, "pug": 100.0, "ragdoll": 10.0, "russian_blue": 95.0, "saint_bernard": 70.0, "samoyed": 85.0, "scottish_terrier": 70.0, "shiba_inu": 80.0, "siamese": 60.0, "sphynx": 60.0, "staffordshire_bull_terrier": 75.0, "wheaten_terrier": 60.0, "yorkshire_terrier": 20.0}, {"abyssinian": 0.0, "american_bulldog": 25.0, "american_pit_bull_terrier": 35.0, "basset_hound": 100.0, "beagle": 20.0, "bengal": 40.0, "birman": 30.0, "bombay": 26.31578947368421, "boxer": 40.0, "british_shorthair": 0.0, "chihuahua": 85.0, "egyptian_mau": 36.8421052631579, "english_cocker_spaniel": 52.63157894736842, "english_setter": 25.0, "german_shorthaired": 40.0, "great_pyrenees": 90.0, "havanese": 10.0, "japanese_chin": 70.0, "keeshond": 15.0, "leonberger": 65.0, "maine_coon": 60.0, "miniature_pinscher": 80.0, "newfoundland": 73.6842105263158, "persian": 20.0, "pomeranian": 75.0, "pug": 100.0, "ragdoll": 10.0, "russian_blue": 90.0, "saint_bernard": 60.0, "samoyed": 75.0, "scottish_terrier": 70.0, "shiba_inu": 85.0, "siamese": 60.0, "sphynx": 50.0, "staffordshire_bull_terrier": 80.0, "wheaten_terrier": 55.0, "yorkshire_terrier": 20.0}, {"abyssinian": 0.0, "american_bulldog": 25.0, "american_pit_bull_terrier": 40.0, "basset_hound": 95.0, "beagle": 20.0, "bengal": 45.0, "birman": 35.0, "bombay": 15.789473684210526, "boxer": 40.0, "british_shorthair": 0.0, "chihuahua": 85.0, "egyptian_mau": 36.8421052631579, "english_cocker_spaniel": 47.36842105263158, "english_setter": 25.0, "german_shorthaired": 35.0, "great_pyrenees": 90.0, "havanese": 15.0, "japanese_chin": 80.0, "keeshond": 15.0, "leonberger": 70.0, "maine_coon": 45.0, "miniature_pinscher": 75.0, "newfoundland": 73.6842105263158, "persian": 40.0, "pomeranian": 60.0, "pug": 100.0, "ragdoll": 10.0, "russian_blue": 90.0, "saint_bernard": 55.0, "samoyed": 75.0, "scottish_terrier": 65.0, "shiba_inu": 80.0, "siamese": 55.0, "sphynx": 30.0, "staffordshire_bull_terrier": 75.0, "wheaten_terrier": 55.0, "yorkshire_terrier": 25.0}, {"abyssinian": 0.0, "american_bulldog": 30.0, "american_pit_bull_terrier": 35.0, "basset_hound": 95.0, "beagle": 20.0, "bengal": 30.0, "birman": 25.0, "bombay": 21.05263157894737, "boxer": 40.0, "british_shorthair": 0.0, "chihuahua": 85.0, "egyptian_mau": 36.8421052631579, "english_cocker_spaniel": 52.63157894736842, "english_setter": 20.0, "german_shorthaired": 40.0, "great_pyrenees": 90.0, "havanese": 10.0, "japanese_chin": 80.0, "keeshond": 15.0, "leonberger": 65.0, "maine_coon": 75.0, "miniature_pinscher": 80.0, "newfoundland": 73.6842105263158, "persian": 20.0, "pomeranian": 65.0, "pug": 100.0, "ragdoll": 10.0, "russian_blue": 95.0, "saint_bernard": 60.0, "samoyed": 85.0, "scottish_terrier": 65.0, "shiba_inu": 80.0, "siamese": 60.0, "sphynx": 50.0, "staffordshire_bull_terrier": 75.0, "wheaten_terrier": 55.0, "yorkshire_terrier": 15.0}, {"abyssinian": 0.0, "american_bulldog": 35.0, "american_pit_bull_terrier": 35.0, "basset_hound": 95.0, "beagle": 20.0, "bengal": 40.0, "birman": 30.0, "bombay": 21.05263157894737, "boxer": 45.0, "british_shorthair": 0.0, "chihuahua": 85.0, "egyptian_mau": 31.57894736842105, "english_cocker_spaniel": 47.36842105263158, "english_setter": 20.0, "german_shorthaired": 40.0, "great_pyrenees": 90.0, "havanese": 15.0, "japanese_chin": 80.0, "keeshond": 15.0, "leonberger": 60.0, "maine_coon": 70.0, "miniature_pinscher": 75.0, "newfoundland": 73.6842105263158, "persian": 25.0, "pomeranian": 65.0, "pug": 100.0, "ragdoll": 10.0, "russian_blue": 95.0, "saint_bernard": 60.0, "samoyed": 85.0, "scottish_terrier": 60.0, "shiba_inu": 85.0, "siamese": 60.0, "sphynx": 60.0, "staffordshire_bull_terrier": 80.0, "wheaten_terrier": 55.0, "yorkshire_terrier": 20.0}, {"abyssinian": 0.0, "american_bulldog": 25.0, "american_pit_bull_terrier": 35.0, "basset_hound": 95.0, "beagle": 20.0, "bengal": 45.0, "birman": 20.0, "bombay": 21.05263157894737, "boxer": 45.0, "british_shorthair": 0.0, "chihuahua": 85.0, "egyptian_mau": 31.57894736842105, "english_cocker_spaniel": 52.63157894736842, "english_setter": 25.0, "german_shorthaired": 45.0, "great_pyrenees": 90.0, "havanese": 15.0, "japanese_chin": 80.0, "keeshond": 10.0, "leonberger": 70.0, "maine_coon": 50.0, "miniature_pinscher": 85.0, "newfoundland": 63.1578947368421, "persian": 35.0, "pomeranian": 65.0, "pug": 100.0, "ragdoll": 15.0, "russian_blue": 95.0, "saint_bernard": 60.0, "samoyed": 90.0, "scottish_terrier": 65.0, "shiba_inu": 80.0, "siamese": 50.0, "sphynx": 45.0, "staffordshire_bull_terrier": 75.0, "wheaten_terrier": 65.0, "yorkshire_terrier": 25.0}, {"abyssinian": 0.0, "american_bulldog": 25.0, "american_pit_bull_terrier": 35.0, "basset_hound": 95.0, "beagle": 20.0, "bengal": 45.0, "birman": 35.0, "bombay": 21.05263157894737, "boxer": 45.0, "british_shorthair": 0.0, "chihuahua": 85.0, "egyptian_mau": 31.57894736842105, "english_cocker_spaniel": 47.36842105263158, "english_setter": 25.0, "german_shorthaired": 40.0, "great_pyrenees": 90.0, "havanese": 10.0, "japanese_chin": 80.0, "keeshond": 15.0, "leonberger": 70.0, "maine_coon": 65.0, "miniature_pinscher": 85.0, "newfoundland": 63.1578947368421, "persian": 30.0, "pomeranian": 60.0, "pug": 100.0, "ragdoll": 10.0, "russian_blue": 95.0, "saint_bernard": 60.0, "samoyed": 90.0, "scottish_terrier": 70.0, "shiba_inu": 85.0, "siamese": 55.0, "sphynx": 65.0, "staffordshire_bull_terrier": 75.0, "wheaten_terrier": 60.0, "yorkshire_terrier": 20.0}, {"abyssinian": 0.0, "american_bulldog": 25.0, "american_pit_bull_terrier": 35.0, "basset_hound": 95.0, "beagle": 20.0, "bengal": 30.0, "birman": 35.0, "bombay": 21.05263157894737, "boxer": 45.0, "british_shorthair": 0.0, "chihuahua": 85.0, "egyptian_mau": 31.57894736842105, "english_cocker_spaniel": 52.63157894736842, "english_setter": 15.0, "german_shorthaired": 40.0, "great_pyrenees": 90.0, "havanese": 15.0, "japanese_chin": 80.0, "keeshond": 15.0, "leonberger": 70.0, "maine_coon": 60.0, "miniature_pinscher": 75.0, "newfoundland": 63.1578947368421, "persian": 30.0, "pomeranian": 60.0, "pug": 100.0, "ragdoll": 10.0, "russian_blue": 90.0, "saint_bernard": 65.0, "samoyed": 85.0, "scottish_terrier": 65.0, "shiba_inu": 80.0, "siamese": 55.0, "sphynx": 75.0, "staffordshire_bull_terrier": 80.0, "wheaten_terrier": 55.0, "yorkshire_terrier": 20.0}, {"abyssinian": 0.0, "american_bulldog": 20.0, "american_pit_bull_terrier": 35.0, "basset_hound": 95.0, "beagle": 20.0, "bengal": 35.0, "birman": 35.0, "bombay": 21.05263157894737, "boxer": 50.0, "british_shorthair": 0.0, "chihuahua": 85.0, "egyptian_mau": 31.57894736842105, "english_cocker_spaniel": 52.63157894736842, "english_setter": 20.0, "german_shorthaired": 40.0, "great_pyrenees": 90.0, "havanese": 10.0, "japanese_chin": 80.0, "keeshond": 15.0, "leonberger": 65.0, "maine_coon": 60.0, "miniature_pinscher": 80.0, "newfoundland": 68.42105263157895, "persian": 25.0, "pomeranian": 70.0, "pug": 100.0, "ragdoll": 10.0, "russian_blue": 95.0, "saint_bernard": 60.0, "samoyed": 85.0, "scottish_terrier": 70.0, "shiba_inu": 80.0, "siamese": 60.0, "sphynx": 55.0, "staffordshire_bull_terrier": 80.0, "wheaten_terrier": 55.0, "yorkshire_terrier": 20.0}, {"abyssinian": 0.0, "american_bulldog": 25.0, "american_pit_bull_terrier": 30.0, "basset_hound": 95.0, "beagle": 20.0, "bengal": 40.0, "birman": 30.0, "bombay": 26.31578947368421, "boxer": 50.0, "british_shorthair": 0.0, "chihuahua": 85.0, "egyptian_mau": 31.57894736842105, "english_cocker_spaniel": 57.89473684210526, "english_setter": 20.0, "german_shorthaired": 35.0, "great_pyrenees": 90.0, "havanese": 15.0, "japanese_chin": 75.0, "keeshond": 20.0, "leonberger": 60.0, "maine_coon": 55.0, "miniature_pinscher": 85.0, "newfoundland": 68.42105263157895, "persian": 30.0, "pomeranian": 65.0, "pug": 100.0, "ragdoll": 10.0, "russian_blue": 95.0, "saint_bernard": 65.0, "samoyed": 85.0, "scottish_terrier": 70.0, "shiba_inu": 85.0, "siamese": 65.0, "sphynx": 50.0, "staffordshire_bull_terrier": 80.0, "wheaten_terrier": 55.0, "yorkshire_terrier": 20.0}, {"abyssinian": 0.0, "american_bulldog": 30.0, "american_pit_bull_terrier": 35.0, "basset_hound": 95.0, "beagle": 20.0, "bengal": 45.0, "birman": 20.0, "bombay": 10.526315789473685, "boxer": 45.0, "british_shorthair": 0.0, "chihuahua": 85.0, "egyptian_mau": 36.8421052631579, "english_cocker_spaniel": 57.89473684210526, "english_setter": 15.0, "german_shorthaired": 40.0, "great_pyrenees": 90.0, "havanese": 10.0, "japanese_chin": 80.0, "keeshond": 15.0, "leonberger": 65.0, "maine_coon": 55.0, "miniature_pinscher": 80.0, "newfoundland": 68.42105263157895, "persian": 30.0, "pomeranian": 65.0, "pug": 100.0, "ragdoll": 10.0, "russian_blue": 95.0, "saint_bernard": 60.0, "samoyed": 85.0, "scottish_terrier": 70.0, "shiba_inu": 80.0, "siamese": 50.0, "sphynx": 50.0, "staffordshire_bull_terrier": 80.0, "wheaten_terrier": 55.0, "yorkshire_terrier": 20.0}, {"abyssinian": 0.0, "american_bulldog": 25.0, "american_pit_bull_terrier": 35.0, "basset_hound": 95.0, "beagle": 20.0, "bengal": 45.0, "birman": 25.0, "bombay": 15.789473684210526, "boxer": 45.0, "british_shorthair": 0.0, "chihuahua": 85.0, "egyptian_mau": 31.57894736842105, "english_cocker_spaniel": 52.63157894736842, "english_setter": 15.0, "german_shorthaired": 45.0, "great_pyrenees": 90.0, "havanese": 15.0, "japanese_chin": 80.0, "keeshond": 15.0, "leonberger": 60.0, "maine_coon": 65.0, "miniature_pinscher": 80.0, "newfoundland": 73.6842105263158, "persian": 20.0, "pomeranian": 60.0, "pug": 100.0, "ragdoll": 10.0, "russian_blue": 95.0, "saint_bernard": 65.0, "samoyed": 85.0, "scottish_terrier": 70.0, "shiba_inu": 80.0, "siamese": 60.0, "sphynx": 55.0, "staffordshire_bull_terrier": 75.0, "wheaten_terrier": 55.0, "yorkshire_terrier": 15.0}, {"abyssinian": 0.0, "american_bulldog": 25.0, "american_pit_bull_terrier": 35.0, "basset_hound": 95.0, "beagle": 20.0, "bengal": 30.0, "birman": 25.0, "bombay": 21.05263157894737, "boxer": 50.0, "british_shorthair": 0.0, "chihuahua": 85.0, "egyptian_mau": 36.8421052631579, "english_cocker_spaniel": 57.89473684210526, "english_setter": 20.0, "german_shorthaired": 35.0, "great_pyrenees": 90.0, "havanese": 15.0, "japanese_chin": 80.0, "keeshond": 15.0, "leonberger": 65.0, "maine_coon": 60.0, "miniature_pinscher": 80.0, "newfoundland": 63.1578947368421, "persian": 40.0, "pomeranian": 65.0, "pug": 100.0, "ragdoll": 10.0, "russian_blue": 95.0, "saint_bernard": 65.0, "samoyed": 85.0, "scottish_terrier": 65.0, "shiba_inu": 80.0, "siamese": 65.0, "sphynx": 55.0, "staffordshire_bull_terrier": 80.0, "wheaten_terrier": 55.0, "yorkshire_terrier": 15.0}, {"abyssinian": 62.244897959183675, "american_bulldog": 34.0, "american_pit_bull_terrier": 65.0, "basset_hound": 58.0, "beagle": 86.0, "bengal": 64.0, "birman": 2.0, "bombay": 1.1363636363636365, "boxer": 18.181818181818183, "british_shorthair": 14.0, "chihuahua": 93.0, "egyptian_mau": 52.577319587628864, "english_cocker_spaniel": 20.0, "english_setter": 60.0, "german_shorthaired": 37.0, "great_pyrenees": 96.0, "havanese": 31.0, "japanese_chin": 83.0, "keeshond": 44.44444444444444, "leonberger": 38.0, "maine_coon": 33.0, "miniature_pinscher": 30.0, "newfoundland": 93.0, "persian": 16.0, "pomeranian": 72.0, "pug": 99.0, "ragdoll": 13.0, "russian_blue": 78.0, "saint_bernard": 47.0, "samoyed": 92.0, "scottish_terrier": 85.85858585858585, "shiba_inu": 94.0, "siamese": 39.0, "sphynx": 81.0, "staffordshire_bull_terrier": 28.089887640449437, "wheaten_terrier": 65.0, "yorkshire_terrier": 50.0}]